{
    "AX": {
        "error": 0.009925394239335793,
        "error_type": "SEM",
        "filter_outliers_dict": {
            "filter_outliers": true,
            "iterations": 1,
            "std_devs": 3,
            "use_iqr_filtering": false,
            "use_standard_deviation_filtering": false
        },
        "fit": "average",
        "fn": 30,
        "include_baseline_error": false,
        "n": 30,
        "outlier_excluded": [],
        "reviewed": true,
        "user_excluded": [],
        "value": -0.024460556792716186
    },
    "CDD": {
        "error": 2.3841556713686233e-05,
        "error_type": "SEM",
        "filter_outliers_dict": {
            "filter_outliers": true,
            "iterations": 1,
            "std_devs": 10,
            "use_iqr_filtering": false,
            "use_standard_deviation_filtering": false
        },
        "fit": "average",
        "fn": 30,
        "include_baseline_error": false,
        "n": 30,
        "outlier_excluded": [],
        "reviewed": true,
        "user_excluded": [],
        "value": 0.00020625180331990123
    },
    "H1": {
        "error": 0.008502511390136027,
        "error_type": "SEM",
        "filter_outliers_dict": {
            "filter_outliers": true,
            "iterations": 1,
            "std_devs": 3,
            "use_iqr_filtering": false,
            "use_standard_deviation_filtering": false
        },
        "fit": "average",
        "fn": 30,
        "include_baseline_error": false,
        "n": 30,
        "outlier_excluded": [],
        "reviewed": true,
        "user_excluded": [],
        "value": 0.03871507914736867
    },
    "H2": {
        "error": 0.05199341551407211,
        "error_type": "SEM",
        "filter_outliers_dict": {
            "filter_outliers": true,
            "iterations": 1,
            "std_devs": 3,
            "use_iqr_filtering": false,
            "use_standard_deviation_filtering": false
        },
        "fit": "average",
        "fn": 30,
        "include_baseline_error": false,
        "n": 30,
        "outlier_excluded": [],
        "reviewed": true,
        "user_excluded": [],
        "value": -0.2393431248764197
    },
    "L1": {
        "error": 0.004457220383751284,
        "error_type": "SEM",
        "filter_outliers_dict": {
            "filter_outliers": true,
            "iterations": 1,
            "std_devs": 3,
            "use_iqr_filtering": false,
            "use_standard_deviation_filtering": false
        },
        "fit": "average",
        "fn": 30,
        "include_baseline_error": false,
        "n": 30,
        "outlier_excluded": [],
        "reviewed": true,
        "user_excluded": [],
        "value": 0.06174805353706082
    },
    "L2": {
        "error": 0.003206124092873404,
        "error_type": "SEM",
        "filter_outliers_dict": {
            "filter_outliers": true,
            "iterations": 1,
            "std_devs": 2
        },
        "fit": "average",
        "value": -0.043961730334819926
    }
}