{
    "Ar36": {
        "error": 0.0003050193678718908,
        "error_type": "",
        "fit": "previous",
        "references": [
            {
                "exclude": false,
                "record_id": "bu-FC-J-16429"
            }
        ],
        "value": 0.019981420950215614
    },
    "Ar37": {
        "error": 0.004552480426503818,
        "error_type": "",
        "fit": "previous",
        "references": [
            {
                "exclude": false,
                "record_id": "bu-FC-J-16429"
            }
        ],
        "value": 0.04993779175778333
    },
    "Ar38": {
        "error": 0.004093321107215192,
        "error_type": "",
        "fit": "previous",
        "references": [
            {
                "exclude": false,
                "record_id": "bu-FC-J-16429"
            }
        ],
        "value": 0.031775559307533244
    },
    "Ar39": {
        "error": 0.019471071083180403,
        "error_type": "",
        "fit": "previous",
        "references": [
            {
                "exclude": false,
                "record_id": "bu-FC-J-16429"
            }
        ],
        "value": 0.06312664507524465
    },
    "Ar40": {
        "error": 0.017418666589256008,
        "error_type": "",
        "fit": "previous",
        "references": [
            {
                "exclude": false,
                "record_id": "bu-FC-J-16429"
            }
        ],
        "value": 3.936143436297404
    },
    "Ar41": {
        "error": 0.02188543792452363,
        "error_type": "",
        "fit": "previous",
        "references": [
            {
                "exclude": false,
                "record_id": "bu-FC-J-16429"
            }
        ],
        "value": 0.025364172559295822
    }
}