{
    "Ar36": {
        "error": 0.0007485475846152155,
        "error_type": "SEM",
        "filter_outliers_dict": {
            "filter_outliers": true,
            "iterations": 1,
            "std_devs": 3,
            "use_iqr_filtering": false,
            "use_standard_deviation_filtering": false
        },
        "fit": "linear",
        "fn": 119,
        "include_baseline_error": true,
        "n": 120,
        "outlier_excluded": [
            77
        ],
        "reviewed": true,
        "user_excluded": [],
        "value": 0.0712609436269808
    },
    "Ar37": {
        "error": 0.006814751508928269,
        "error_type": "SEM",
        "filter_outliers_dict": {
            "filter_outliers": true,
            "iterations": 1,
            "std_devs": 3,
            "use_iqr_filtering": false,
            "use_standard_deviation_filtering": false
        },
        "fit": "linear",
        "fn": 119,
        "include_baseline_error": true,
        "n": 120,
        "outlier_excluded": [
            0
        ],
        "reviewed": true,
        "user_excluded": [],
        "value": -0.010332992644177806
    },
    "Ar38": {
        "error": 0.007444288022209288,
        "error_type": "SEM",
        "filter_outliers_dict": {
            "filter_outliers": true,
            "iterations": 1,
            "std_devs": 3,
            "use_iqr_filtering": false,
            "use_standard_deviation_filtering": false
        },
        "fit": "linear",
        "fn": 120,
        "include_baseline_error": true,
        "n": 120,
        "outlier_excluded": [],
        "reviewed": true,
        "user_excluded": [],
        "value": 2.064422291938418
    },
    "Ar39": {
        "error": 0.027004766198742453,
        "error_type": "SEM",
        "filter_outliers_dict": {
            "filter_outliers": true,
            "iterations": 1,
            "std_devs": 3,
            "use_iqr_filtering": false,
            "use_standard_deviation_filtering": false
        },
        "fit": "linear",
        "fn": 120,
        "include_baseline_error": true,
        "n": 120,
        "outlier_excluded": [],
        "reviewed": true,
        "user_excluded": [],
        "value": 160.5528271958683
    },
    "Ar40": {
        "error": 0.0745883388061179,
        "error_type": "SEM",
        "filter_outliers_dict": {
            "filter_outliers": true,
            "iterations": 1,
            "std_devs": 3,
            "use_iqr_filtering": false,
            "use_standard_deviation_filtering": false
        },
        "fit": "linear",
        "fn": 120,
        "include_baseline_error": true,
        "n": 120,
        "outlier_excluded": [],
        "reviewed": true,
        "user_excluded": [],
        "value": 1087.5861921042606
    },
    "Ar41": {
        "error": 0.026971069655213387,
        "error_type": "SEM",
        "filter_outliers_dict": {
            "filter_outliers": true,
            "iterations": 1,
            "std_devs": 2
        },
        "fit": "average",
        "value": -0.13055011601795571
    }
}